{"chunk_definitions":[{"row":11,"row_count":1,"visible":true,"expansion_state":0,"options":{"engine":"r","label":"setup","include":false},"document_id":"780CBE60","chunk_id":"csetup_chunk","chunk_label":"setup"},{"row":16,"row_count":1,"visible":true,"expansion_state":0,"options":{"engine":"r","label":"unnamed-chunk-6"},"document_id":"780CBE60","chunk_id":"c8rpufojfgiao","chunk_label":"unnamed-chunk-1"},{"row":31,"row_count":1,"visible":true,"expansion_state":0,"options":{"engine":"r","label":"unnamed-chunk-5"},"document_id":"780CBE60","chunk_id":"can4jy7sn5g4i","chunk_label":"unnamed-chunk-2"}],"doc_write_time":1695819222,"working_dir":null,"default_chunk_options":{"echo":true}}